kafka_topics/__init__.py
kafka_topics/topics.py
kafka_topics-0.1.4.dist-info/METADATA
kafka_topics-0.1.4.dist-info/WHEEL
kafka_topics-0.1.4.dist-info/top_level.txt
kafka_topics-0.1.4.dist-info/RECORD
