Metadata-Version: 2.4
Name: kafka-topics
Version: 0.1.4
Summary: Centralized Kafka topic constants for Pack Bridge services
Author-email: Pack Bridge <tech@pack-bridge.com>
Project-URL: Homepage, https://www.pack-bridge.com
Project-URL: Bug Tracker, https://github.com/pack-bridge/pack-bridge/issues
Classifier: Programming Language :: Python :: 3
Classifier: License :: OSI Approved :: MIT License
Classifier: Operating System :: OS Independent
Requires-Python: >=3.9
